pyts2/__init__.py
pyts2/_version.py
pyts2/commandline.py
pyts2/filelock.py
pyts2/removalist.py
pyts2/time.py
pyts2/timestream.py
pyts2/utils.py
pyts2/data/Monoid-Bold-HalfLoose-0-1-NoCalt.ttf
pyts2/pipeline/__init__.py
pyts2/pipeline/align_time.py
pyts2/pipeline/audit.py
pyts2/pipeline/backblaze.py
pyts2/pipeline/base.py
pyts2/pipeline/gigavision.py
pyts2/pipeline/imageio.py
pyts2/pipeline/influxdb.py
pyts2/pipeline/jupyter.py
pyts2/pipeline/phenocam.py
pyts2/pipeline/resize.py
pyts2/pipeline/rmscript.py
pyts2/pipeline/roitracker.py
pyts2/pipeline/telegraf.py
pyts2/pipeline/verify.py
pyts2/pipeline/video.py
pyts2/scripts/__init__.py
pyts2/scripts/findpairs.py
pyts2/scripts/imgscan.py
pyts2-0.4.8.data/data/requirements-extended.txt
pyts2-0.4.8.data/data/requirements.txt
tests/__init__.py
tests/data.py
tests/test_file.py
tests/test_pipeline.py
tests/test_resize.py
tests/test_time.py
tests/test_timestream.py
tests/utils.py
pyts2-0.4.8.dist-info/LICENSE
pyts2-0.4.8.dist-info/METADATA
pyts2-0.4.8.dist-info/WHEEL
pyts2-0.4.8.dist-info/entry_points.txt
pyts2-0.4.8.dist-info/top_level.txt
pyts2-0.4.8.dist-info/RECORD
